[
    {
        "id": 4762,
        "date": "2021-02-27T10:55:22",
        "date_gmt": "2021-02-27T10:55:22",
        "guid": {
            "rendered": "http:\/\/angular.foobrdigital.com\/?p=4762"
        },
        "modified": "2021-02-27T10:55:22",
        "modified_gmt": "2021-02-27T10:55:22",
        "slug": "intro-10",
        "status": "publish",
        "type": "post",
        "link": "https:\/\/angular.foobrdigital.com\/intro-10\/",
        "title": {
            "rendered": "Intro"
        },
        "content": {
            "rendered": "\n<p>Just like Web and the entire web ecosystem, Angular is continuously improving. Angular balances continuous improvement with a strong focus on stability and making updates easy. Keeping your Angular app up-to-date enables you to take advantage of leading-edge new features, as well as optimizations and bug fixes.<\/p>\n\n\n\n<p>This document contains information and resources to help you keep your Angular apps and libraries up-to-date.<\/p>\n\n\n\n<p>For information about our versioning policy and practices\u2014including support and deprecation practices, as well as the release schedule\u2014see&nbsp;<a href=\"https:\/\/angular.io\/guide\/releases\">Angular versioning and releases<\/a>.<\/p>\n\n\n\n<p>If you are currently using AngularJS, see\u00a0Upgrading from AngularJS.\u00a0<em>AngularJS<\/em>\u00a0is the name for all v1.x versions of Angular.<\/p>\n",
            "protected": false
        },
        "excerpt": {
            "rendered": "<p>Just like Web and the entire web ecosystem, Angular is continuously improving. Angular balances continuous improvement with a strong focus on stability and making updates easy. Keeping your Angular app up-to-date enables you to take advantage of leading-edge new features, as well as optimizations and bug fixes. This document contains information and resources to help [&hellip;]<\/p>\n",
            "protected": false
        },
        "author": 2,
        "featured_media": 0,
        "comment_status": "open",
        "ping_status": "open",
        "sticky": false,
        "template": "",
        "format": "standard",
        "meta": [],
        "categories": [
            238
        ],
        "tags": [],
        "_links": {
            "self": [
                {
                    "href": "https:\/\/angular.foobrdigital.com\/wp-json\/wp\/v2\/posts\/4762"
                }
            ],
            "collection": [
                {
                    "href": "https:\/\/angular.foobrdigital.com\/wp-json\/wp\/v2\/posts"
                }
            ],
            "about": [
                {
                    "href": "https:\/\/angular.foobrdigital.com\/wp-json\/wp\/v2\/types\/post"
                }
            ],
            "author": [
                {
                    "embeddable": true,
                    "href": "https:\/\/angular.foobrdigital.com\/wp-json\/wp\/v2\/users\/2"
                }
            ],
            "replies": [
                {
                    "embeddable": true,
                    "href": "https:\/\/angular.foobrdigital.com\/wp-json\/wp\/v2\/comments?post=4762"
                }
            ],
            "version-history": [
                {
                    "count": 1,
                    "href": "https:\/\/angular.foobrdigital.com\/wp-json\/wp\/v2\/posts\/4762\/revisions"
                }
            ],
            "predecessor-version": [
                {
                    "id": 4763,
                    "href": "https:\/\/angular.foobrdigital.com\/wp-json\/wp\/v2\/posts\/4762\/revisions\/4763"
                }
            ],
            "wp:attachment": [
                {
                    "href": "https:\/\/angular.foobrdigital.com\/wp-json\/wp\/v2\/media?parent=4762"
                }
            ],
            "wp:term": [
                {
                    "taxonomy": "category",
                    "embeddable": true,
                    "href": "https:\/\/angular.foobrdigital.com\/wp-json\/wp\/v2\/categories?post=4762"
                },
                {
                    "taxonomy": "post_tag",
                    "embeddable": true,
                    "href": "https:\/\/angular.foobrdigital.com\/wp-json\/wp\/v2\/tags?post=4762"
                }
            ],
            "curies": [
                {
                    "name": "wp",
                    "href": "https:\/\/api.w.org\/{rel}",
                    "templated": true
                }
            ]
        }
    },
    {
        "id": 4761,
        "date": "2021-02-27T10:55:53",
        "date_gmt": "2021-02-27T10:55:53",
        "guid": {
            "rendered": "http:\/\/angular.foobrdigital.com\/?p=4761"
        },
        "modified": "2021-02-27T10:55:53",
        "modified_gmt": "2021-02-27T10:55:53",
        "slug": "learning-about-new-features",
        "status": "publish",
        "type": "post",
        "link": "https:\/\/angular.foobrdigital.com\/learning-about-new-features\/",
        "title": {
            "rendered": "Learning about new features"
        },
        "content": {
            "rendered": "\n<p>What&#8217;s new? What&#8217;s changed? We share the most important things you need to know on the Angular blog in\u00a0release announcements.<\/p>\n\n\n\n<p>To review a complete list of changes, organized by version, see the\u00a0Angular change log.<\/p>\n",
            "protected": false
        },
        "excerpt": {
            "rendered": "<p>What&#8217;s new? What&#8217;s changed? We share the most important things you need to know on the Angular blog in\u00a0release announcements. To review a complete list of changes, organized by version, see the\u00a0Angular change log.<\/p>\n",
            "protected": false
        },
        "author": 2,
        "featured_media": 0,
        "comment_status": "open",
        "ping_status": "open",
        "sticky": false,
        "template": "",
        "format": "standard",
        "meta": [],
        "categories": [
            238
        ],
        "tags": [],
        "_links": {
            "self": [
                {
                    "href": "https:\/\/angular.foobrdigital.com\/wp-json\/wp\/v2\/posts\/4761"
                }
            ],
            "collection": [
                {
                    "href": "https:\/\/angular.foobrdigital.com\/wp-json\/wp\/v2\/posts"
                }
            ],
            "about": [
                {
                    "href": "https:\/\/angular.foobrdigital.com\/wp-json\/wp\/v2\/types\/post"
                }
            ],
            "author": [
                {
                    "embeddable": true,
                    "href": "https:\/\/angular.foobrdigital.com\/wp-json\/wp\/v2\/users\/2"
                }
            ],
            "replies": [
                {
                    "embeddable": true,
                    "href": "https:\/\/angular.foobrdigital.com\/wp-json\/wp\/v2\/comments?post=4761"
                }
            ],
            "version-history": [
                {
                    "count": 1,
                    "href": "https:\/\/angular.foobrdigital.com\/wp-json\/wp\/v2\/posts\/4761\/revisions"
                }
            ],
            "predecessor-version": [
                {
                    "id": 4764,
                    "href": "https:\/\/angular.foobrdigital.com\/wp-json\/wp\/v2\/posts\/4761\/revisions\/4764"
                }
            ],
            "wp:attachment": [
                {
                    "href": "https:\/\/angular.foobrdigital.com\/wp-json\/wp\/v2\/media?parent=4761"
                }
            ],
            "wp:term": [
                {
                    "taxonomy": "category",
                    "embeddable": true,
                    "href": "https:\/\/angular.foobrdigital.com\/wp-json\/wp\/v2\/categories?post=4761"
                },
                {
                    "taxonomy": "post_tag",
                    "embeddable": true,
                    "href": "https:\/\/angular.foobrdigital.com\/wp-json\/wp\/v2\/tags?post=4761"
                }
            ],
            "curies": [
                {
                    "name": "wp",
                    "href": "https:\/\/api.w.org\/{rel}",
                    "templated": true
                }
            ]
        }
    },
    {
        "id": 4760,
        "date": "2021-02-27T10:56:04",
        "date_gmt": "2021-02-27T10:56:04",
        "guid": {
            "rendered": "http:\/\/angular.foobrdigital.com\/?p=4760"
        },
        "modified": "2021-02-27T10:56:04",
        "modified_gmt": "2021-02-27T10:56:04",
        "slug": "checking-your-version-of-angular",
        "status": "publish",
        "type": "post",
        "link": "https:\/\/angular.foobrdigital.com\/checking-your-version-of-angular\/",
        "title": {
            "rendered": "Checking your version of Angular"
        },
        "content": {
            "rendered": "\n<p>To check your app&#8217;s version of Angular: From within your project directory, use the\u00a0<code>ng version<\/code>\u00a0command.<\/p>\n",
            "protected": false
        },
        "excerpt": {
            "rendered": "<p>To check your app&#8217;s version of Angular: From within your project directory, use the\u00a0ng version\u00a0command.<\/p>\n",
            "protected": false
        },
        "author": 2,
        "featured_media": 0,
        "comment_status": "open",
        "ping_status": "open",
        "sticky": false,
        "template": "",
        "format": "standard",
        "meta": [],
        "categories": [
            238
        ],
        "tags": [],
        "_links": {
            "self": [
                {
                    "href": "https:\/\/angular.foobrdigital.com\/wp-json\/wp\/v2\/posts\/4760"
                }
            ],
            "collection": [
                {
                    "href": "https:\/\/angular.foobrdigital.com\/wp-json\/wp\/v2\/posts"
                }
            ],
            "about": [
                {
                    "href": "https:\/\/angular.foobrdigital.com\/wp-json\/wp\/v2\/types\/post"
                }
            ],
            "author": [
                {
                    "embeddable": true,
                    "href": "https:\/\/angular.foobrdigital.com\/wp-json\/wp\/v2\/users\/2"
                }
            ],
            "replies": [
                {
                    "embeddable": true,
                    "href": "https:\/\/angular.foobrdigital.com\/wp-json\/wp\/v2\/comments?post=4760"
                }
            ],
            "version-history": [
                {
                    "count": 1,
                    "href": "https:\/\/angular.foobrdigital.com\/wp-json\/wp\/v2\/posts\/4760\/revisions"
                }
            ],
            "predecessor-version": [
                {
                    "id": 4765,
                    "href": "https:\/\/angular.foobrdigital.com\/wp-json\/wp\/v2\/posts\/4760\/revisions\/4765"
                }
            ],
            "wp:attachment": [
                {
                    "href": "https:\/\/angular.foobrdigital.com\/wp-json\/wp\/v2\/media?parent=4760"
                }
            ],
            "wp:term": [
                {
                    "taxonomy": "category",
                    "embeddable": true,
                    "href": "https:\/\/angular.foobrdigital.com\/wp-json\/wp\/v2\/categories?post=4760"
                },
                {
                    "taxonomy": "post_tag",
                    "embeddable": true,
                    "href": "https:\/\/angular.foobrdigital.com\/wp-json\/wp\/v2\/tags?post=4760"
                }
            ],
            "curies": [
                {
                    "name": "wp",
                    "href": "https:\/\/api.w.org\/{rel}",
                    "templated": true
                }
            ]
        }
    },
    {
        "id": 4759,
        "date": "2021-02-27T10:57:49",
        "date_gmt": "2021-02-27T10:57:49",
        "guid": {
            "rendered": "http:\/\/angular.foobrdigital.com\/?p=4759"
        },
        "modified": "2021-02-27T10:57:49",
        "modified_gmt": "2021-02-27T10:57:49",
        "slug": "finding-the-current-version-of-angular",
        "status": "publish",
        "type": "post",
        "link": "https:\/\/angular.foobrdigital.com\/finding-the-current-version-of-angular\/",
        "title": {
            "rendered": "Finding the current version of Angular"
        },
        "content": {
            "rendered": "\n<p>The most recent stable released version of Angular appears in the\u00a0Angular documentation\u00a0at the bottom of the left side navigation. For example,\u00a0<code>stable (v5.2.9)<\/code>.<\/p>\n\n\n\n<p>You can also find the most current version of Angular by using the CLI command\u00a0<code>ng update<\/code>. By default,\u00a0<code>ng update<\/code>(without additional arguments) lists the updates that are available to you.<\/p>\n",
            "protected": false
        },
        "excerpt": {
            "rendered": "<p>The most recent stable released version of Angular appears in the\u00a0Angular documentation\u00a0at the bottom of the left side navigation. For example,\u00a0stable (v5.2.9). You can also find the most current version of Angular by using the CLI command\u00a0ng update. By default,\u00a0ng update(without additional arguments) lists the updates that are available to you.<\/p>\n",
            "protected": false
        },
        "author": 2,
        "featured_media": 0,
        "comment_status": "open",
        "ping_status": "open",
        "sticky": false,
        "template": "",
        "format": "standard",
        "meta": [],
        "categories": [
            238
        ],
        "tags": [],
        "_links": {
            "self": [
                {
                    "href": "https:\/\/angular.foobrdigital.com\/wp-json\/wp\/v2\/posts\/4759"
                }
            ],
            "collection": [
                {
                    "href": "https:\/\/angular.foobrdigital.com\/wp-json\/wp\/v2\/posts"
                }
            ],
            "about": [
                {
                    "href": "https:\/\/angular.foobrdigital.com\/wp-json\/wp\/v2\/types\/post"
                }
            ],
            "author": [
                {
                    "embeddable": true,
                    "href": "https:\/\/angular.foobrdigital.com\/wp-json\/wp\/v2\/users\/2"
                }
            ],
            "replies": [
                {
                    "embeddable": true,
                    "href": "https:\/\/angular.foobrdigital.com\/wp-json\/wp\/v2\/comments?post=4759"
                }
            ],
            "version-history": [
                {
                    "count": 1,
                    "href": "https:\/\/angular.foobrdigital.com\/wp-json\/wp\/v2\/posts\/4759\/revisions"
                }
            ],
            "predecessor-version": [
                {
                    "id": 4766,
                    "href": "https:\/\/angular.foobrdigital.com\/wp-json\/wp\/v2\/posts\/4759\/revisions\/4766"
                }
            ],
            "wp:attachment": [
                {
                    "href": "https:\/\/angular.foobrdigital.com\/wp-json\/wp\/v2\/media?parent=4759"
                }
            ],
            "wp:term": [
                {
                    "taxonomy": "category",
                    "embeddable": true,
                    "href": "https:\/\/angular.foobrdigital.com\/wp-json\/wp\/v2\/categories?post=4759"
                },
                {
                    "taxonomy": "post_tag",
                    "embeddable": true,
                    "href": "https:\/\/angular.foobrdigital.com\/wp-json\/wp\/v2\/tags?post=4759"
                }
            ],
            "curies": [
                {
                    "name": "wp",
                    "href": "https:\/\/api.w.org\/{rel}",
                    "templated": true
                }
            ]
        }
    },
    {
        "id": 4758,
        "date": "2021-02-27T10:58:14",
        "date_gmt": "2021-02-27T10:58:14",
        "guid": {
            "rendered": "http:\/\/angular.foobrdigital.com\/?p=4758"
        },
        "modified": "2021-02-27T10:58:14",
        "modified_gmt": "2021-02-27T10:58:14",
        "slug": "updating-your-environment-and-apps",
        "status": "publish",
        "type": "post",
        "link": "https:\/\/angular.foobrdigital.com\/updating-your-environment-and-apps\/",
        "title": {
            "rendered": "Updating your environment and apps"
        },
        "content": {
            "rendered": "\n<p>To make updating easy, we provide complete instructions in the interactive\u00a0Angular Update Guide.<\/p>\n\n\n\n<p>The Angular Update Guide provides customized update instructions, based on the current and target versions that you specify. It includes basic and advanced update paths, to match the complexity of your applications. It also includes troubleshooting information and any recommended manual changes to help you get the most out of the new release.<\/p>\n\n\n\n<p>For simple updates, the CLI command\u00a0<code>ng update<\/code>\u00a0is all you need. Without additional arguments,\u00a0<code>ng update<\/code>\u00a0lists the updates that are available to you and provides recommended steps to update your application to the most current version.<\/p>\n\n\n\n<p>Angular Versioning and Releases\u00a0describes the level of change that you can expect based a release&#8217;s version number. It also describes supported update paths.<\/p>\n",
            "protected": false
        },
        "excerpt": {
            "rendered": "<p>To make updating easy, we provide complete instructions in the interactive\u00a0Angular Update Guide. The Angular Update Guide provides customized update instructions, based on the current and target versions that you specify. It includes basic and advanced update paths, to match the complexity of your applications. It also includes troubleshooting information and any recommended manual changes [&hellip;]<\/p>\n",
            "protected": false
        },
        "author": 2,
        "featured_media": 0,
        "comment_status": "open",
        "ping_status": "open",
        "sticky": false,
        "template": "",
        "format": "standard",
        "meta": [],
        "categories": [
            238
        ],
        "tags": [],
        "_links": {
            "self": [
                {
                    "href": "https:\/\/angular.foobrdigital.com\/wp-json\/wp\/v2\/posts\/4758"
                }
            ],
            "collection": [
                {
                    "href": "https:\/\/angular.foobrdigital.com\/wp-json\/wp\/v2\/posts"
                }
            ],
            "about": [
                {
                    "href": "https:\/\/angular.foobrdigital.com\/wp-json\/wp\/v2\/types\/post"
                }
            ],
            "author": [
                {
                    "embeddable": true,
                    "href": "https:\/\/angular.foobrdigital.com\/wp-json\/wp\/v2\/users\/2"
                }
            ],
            "replies": [
                {
                    "embeddable": true,
                    "href": "https:\/\/angular.foobrdigital.com\/wp-json\/wp\/v2\/comments?post=4758"
                }
            ],
            "version-history": [
                {
                    "count": 1,
                    "href": "https:\/\/angular.foobrdigital.com\/wp-json\/wp\/v2\/posts\/4758\/revisions"
                }
            ],
            "predecessor-version": [
                {
                    "id": 4767,
                    "href": "https:\/\/angular.foobrdigital.com\/wp-json\/wp\/v2\/posts\/4758\/revisions\/4767"
                }
            ],
            "wp:attachment": [
                {
                    "href": "https:\/\/angular.foobrdigital.com\/wp-json\/wp\/v2\/media?parent=4758"
                }
            ],
            "wp:term": [
                {
                    "taxonomy": "category",
                    "embeddable": true,
                    "href": "https:\/\/angular.foobrdigital.com\/wp-json\/wp\/v2\/categories?post=4758"
                },
                {
                    "taxonomy": "post_tag",
                    "embeddable": true,
                    "href": "https:\/\/angular.foobrdigital.com\/wp-json\/wp\/v2\/tags?post=4758"
                }
            ],
            "curies": [
                {
                    "name": "wp",
                    "href": "https:\/\/api.w.org\/{rel}",
                    "templated": true
                }
            ]
        }
    }
]